yv_utils/__init__.py
yv_utils/main/__init__.py
yv_utils/main/main.py
yv_utils/main/nlp_help.py
yv_utils/main/scripts.py
yv_utils-1.11.dist-info/LICENSE.txt
yv_utils-1.11.dist-info/METADATA
yv_utils-1.11.dist-info/WHEEL
yv_utils-1.11.dist-info/top_level.txt
yv_utils-1.11.dist-info/RECORD
